cabinet_relay
