Metadata-Version: 1.0
Name: cabinet-relay
Version: 0.14
Summary: cabinet cabinet_relay
Home-page: UNKNOWN
Author: hewitt
Author-email: pypi_user@163.com
License: MIT
Platform: UNKNOWN
